french_tax_mcp/__init__.py
french_tax_mcp/constants.py
french_tax_mcp/helpers.py
french_tax_mcp/report_generator.py
french_tax_mcp/server.py
french_tax_mcp/analyzers/__init__.py
french_tax_mcp/analyzers/income_analyzer.py
french_tax_mcp/scrapers/__init__.py
french_tax_mcp/scrapers/base_scraper.py
french_tax_mcp/scrapers/impots_scraper.py
french_tax_mcp/scrapers/legal_scraper.py
french_tax_mcp/scrapers/markitdown_scraper.py
french_tax_mcp/scrapers/service_public_scraper.py
french_tax_mcp/static/__init__.py
french_tax_mcp/static/templates/__init__.py
french_tax_mcp/static/templates/report_template.py
iflow_mcp_cornelcroi_french_tax_mcp-1.1.0.dist-info/METADATA
iflow_mcp_cornelcroi_french_tax_mcp-1.1.0.dist-info/WHEEL
iflow_mcp_cornelcroi_french_tax_mcp-1.1.0.dist-info/entry_points.txt
iflow_mcp_cornelcroi_french_tax_mcp-1.1.0.dist-info/licenses/LICENSE
iflow_mcp_cornelcroi_french_tax_mcp-1.1.0.dist-info/RECORD
