Metadata-Version: 2.4
Name: iflow-mcp_cornelcroi_french-tax-mcp
Version: 1.1.0
Summary: MCP server for French tax calculations and information
Project-URL: Homepage, https://github.com/cornelcroi/french-tax-mcp
Project-URL: Documentation, https://github.com/cornelcroi/french-tax-mcp#readme
Project-URL: Repository, https://github.com/cornelcroi/french-tax-mcp.git
Project-URL: Issues, https://github.com/cornelcroi/french-tax-mcp/issues
Project-URL: Changelog, https://github.com/cornelcroi/french-tax-mcp/releases
Author: Corneliu CROITORU
Maintainer: Corneliu CROITORU
License: Apache License 2.0
License-File: LICENSE
Keywords: ai-assistant,france,french-tax,impots,mcp,model-context-protocol,tax-calculation,tax-scraper
Classifier: Development Status :: 5 - Production/Stable
Classifier: Intended Audience :: Developers
Classifier: Intended Audience :: Financial and Insurance Industry
Classifier: License :: OSI Approved :: Apache Software License
Classifier: Operating System :: OS Independent
Classifier: Programming Language :: Python :: 3
Classifier: Programming Language :: Python :: 3.10
Classifier: Programming Language :: Python :: 3.11
Classifier: Programming Language :: Python :: 3.12
Classifier: Topic :: Internet :: WWW/HTTP :: Dynamic Content
Classifier: Topic :: Office/Business :: Financial :: Accounting
Classifier: Topic :: Software Development :: Libraries :: Python Modules
Classifier: Typing :: Typed
Requires-Python: >=3.10
Requires-Dist: beautifulsoup4>=4.12.0
Requires-Dist: fastmcp>=0.1.0
Requires-Dist: httpx>=0.24.0
Requires-Dist: lxml>=4.9.0
Requires-Dist: markitdown>=0.1.3
Requires-Dist: pydantic>=2.0.0
Provides-Extra: dev
Requires-Dist: mypy>=1.0.0; extra == 'dev'
Requires-Dist: pytest-asyncio>=0.21.0; extra == 'dev'
Requires-Dist: pytest-cov>=4.0.0; extra == 'dev'
Requires-Dist: pytest>=7.0.0; extra == 'dev'
Requires-Dist: types-beautifulsoup4>=4.12.0; extra == 'dev'
